HardenedSteel/__init__.py
HardenedSteel/facades/__init__.py
HardenedSteel/facades/binaries/__init__.py
HardenedSteel/facades/binaries/random_binary_generation.py
HardenedSteel/facades/booleans/__init__.py
HardenedSteel/facades/booleans/random_boolean_generation.py
HardenedSteel/facades/integers/__init__.py
HardenedSteel/facades/integers/random_number_generation.py
HardenedSteel/facades/integers/states.py
HardenedSteel/facades/texts/__init__.py
HardenedSteel/facades/texts/exceptions.py
HardenedSteel/facades/texts/random_text_generation.py
HardenedSteel/facades/texts/characters/__init__.py
HardenedSteel/facades/texts/characters/ranges.py
HardenedSteel/facades/types/__init__.py
HardenedSteel/facades/types/by_types.py
HardenedSteel/globals/__init__.py
HardenedSteel/globals/singletons/SingletonSystenRandom.py
HardenedSteel/globals/singletons/__init__.py
HardenedSteel/globals/vars/__init__.py
HardenedSteel/globals/vars/bits.py
HardenedSteel/globals/vars/integer.py
HardenedSteel/objects/__init__.py
HardenedSteel/objects/counters/__init__.py
HardenedSteel/objects/counters/counter.py
HardenedSteel/objects/counters/limit.py
hardened_steel-0.0.10.dist-info/METADATA
hardened_steel-0.0.10.dist-info/WHEEL
hardened_steel-0.0.10.dist-info/top_level.txt
hardened_steel-0.0.10.dist-info/RECORD
